README.md
setup.py
flood_tool/__init__.py
flood_tool/analysis.py
flood_tool/geo.py
flood_tool/live.py
flood_tool/mapping.py
flood_tool/tool.py
msoifloodc.egg-info/PKG-INFO
msoifloodc.egg-info/SOURCES.txt
msoifloodc.egg-info/dependency_links.txt
msoifloodc.egg-info/top_level.txt